{
	"class" : {
		"fieldsDesc" : "MarianoMartinezPeck 3/30/2016 21:14",
		"initialize" : "MarianoMartinezPeck 3/30/2016 20:48" },
	"instance" : {
		"argCount" : "MarianoMartinezPeck 3/30/2016 21:37",
		"argCount:" : "MarianoMartinezPeck 3/30/2016 21:37",
		"args" : "MarianoMartinezPeck 3/30/2016 21:37",
		"args:" : "MarianoMartinezPeck 3/30/2016 21:37",
		"asLocalObjectFor:" : "dkh 3/4/2016 09:59",
		"asLocalObjectFor:ifNotConverted:" : "MarianoMartinezPeck 3/29/2016 22:21",
		"category" : "MarianoMartinezPeck 3/30/2016 21:37",
		"category:" : "MarianoMartinezPeck 3/30/2016 21:37",
		"context" : "MarianoMartinezPeck 3/30/2016 21:37",
		"context:" : "MarianoMartinezPeck 3/30/2016 21:37",
		"exceptionObj" : "MarianoMartinezPeck 3/30/2016 21:37",
		"exceptionObj:" : "MarianoMartinezPeck 3/30/2016 21:37",
		"fatal" : "MarianoMartinezPeck 3/30/2016 21:37",
		"fatal:" : "MarianoMartinezPeck 3/30/2016 21:37",
		"message" : "MarianoMartinezPeck 3/30/2016 21:37",
		"message:" : "MarianoMartinezPeck 3/30/2016 21:37",
		"number" : "MarianoMartinezPeck 3/30/2016 21:37",
		"number:" : "MarianoMartinezPeck 3/30/2016 21:37",
		"printOn:" : "dkh 2/16/2016 09:23" } }
